django_model_helper/__init__.py
django_model_helper/actions.py
django_model_helper/admin.py
django_model_helper/apps.py
django_model_helper/models.py
django_model_helper/schemas.py
django_model_helper/settings.py
django_model_helper/tests.py
django_model_helper/version.py
django_model_helper/views.py
django_model_helper/locale/zh_Hans/LC_MESSAGES/django.mo
django_model_helper/locale/zh_Hans/LC_MESSAGES/django.po
django_model_helper/migrations/__init__.py
django_model_helper-0.2.3.dist-info/licenses/LICENSE
django_model_helper-0.2.3.dist-info/METADATA
django_model_helper-0.2.3.dist-info/WHEEL
django_model_helper-0.2.3.dist-info/top_level.txt
django_model_helper-0.2.3.dist-info/RECORD
