Metadata-Version: 2.4
Name: django-model-helper
Version: 0.2.3
Summary: Helpful django abstract models collection.
Author: Li HuiTao
Maintainer: Li HuiTao
License: Apache License, Version 2.0
Keywords: django-model-helper
Classifier: Development Status :: 5 - Production/Stable
Classifier: Intended Audience :: Developers
Classifier: Topic :: Software Development :: Libraries :: Python Modules
Classifier: License :: OSI Approved :: Apache Software License
Classifier: Programming Language :: Python :: 3
Classifier: Programming Language :: Python :: 3 :: Only
License-File: LICENSE
Requires-Dist: zenutils
Requires-Dist: bizerror
Requires-Dist: PyYAML
Requires-Dist: pydantic
Requires-Dist: django
Requires-Dist: django-environment-settings
Requires-Dist: django-mptt
Requires-Dist: django-safe-fields
Dynamic: author
Dynamic: classifier
Dynamic: description
Dynamic: description-content-type
Dynamic: keywords
Dynamic: license
Dynamic: license-file
Dynamic: maintainer
Dynamic: requires-dist
Dynamic: summary
